autospark_kit/__init__.py
autospark_kit/config/__init__.py
autospark_kit/config/config.py
autospark_kit/lib/__init__.py
autospark_kit/lib/logger.py
autospark_kit/tools/__init__.py
autospark_kit/tools/base_tool.py
autospark_kit/tools/base_tool2.py
autospark_kit-0.0.3.dist-info/METADATA
autospark_kit-0.0.3.dist-info/WHEEL
autospark_kit-0.0.3.dist-info/RECORD
