Metadata-Version: 2.1
Name: autospark-kit
Version: 0.0.3
Summary: a iflytek autospark dev kit library ...
License: Apache License 2
Author: ybyang
Author-email: ybyang7@iflytek.com
Requires-Python: >3.7
Classifier: License :: Other/Proprietary License
Classifier: Programming Language :: Python :: 3
Classifier: Programming Language :: Python :: 3.8
Classifier: Programming Language :: Python :: 3.9
Classifier: Programming Language :: Python :: 3.10
Classifier: Programming Language :: Python :: 3.11
Requires-Dist: PyYAML (==6.0)
Requires-Dist: pydantic (==1.10.8)
